hforl/__init__.py
hforl/agent.py
hforl/loss.py
hforl/memory.py
hforl/policy.py
hforl/trainer.py
hforl/agents/__init__.py
hforl/agents/basic.py
hforl/agents/core.py
hforl/agents/ddqn.py
hforl/agents/dqn.py
hforl/agents/static.py
hforl/explorers/__init__.py
hforl/explorers/ou.py
hforl-0.0.2.dist-info/DESCRIPTION.rst
hforl-0.0.2.dist-info/METADATA
hforl-0.0.2.dist-info/RECORD
hforl-0.0.2.dist-info/WHEEL
hforl-0.0.2.dist-info/metadata.json
hforl-0.0.2.dist-info/top_level.txt
