Metadata-Version: 2.0
Name: hforl
Version: 0.0.2
Summary: UNKNOWN
Home-page: UNKNOWN
Author: sho-kw
Author-email: UNKNOWN
License: UNKNOWN
Platform: UNKNOWN
Requires-Dist: Keras (>=2.0.0)
